vegacandle4/__init__.py
vegacandle4/addfunc.py
example_pkg_vegacandle4-0.1.1.dist-info/LICENSE
example_pkg_vegacandle4-0.1.1.dist-info/METADATA
example_pkg_vegacandle4-0.1.1.dist-info/WHEEL
example_pkg_vegacandle4-0.1.1.dist-info/entry_points.txt
example_pkg_vegacandle4-0.1.1.dist-info/top_level.txt
example_pkg_vegacandle4-0.1.1.dist-info/RECORD
